ls_sec/__init__.py
ls_sec/core.py
ls_sec/websocket.py
ls_sec/derivatives/__init__.py
ls_sec/derivatives/_market.py
ls_sec/sector/__init__.py
ls_sec/sector/_market.py
ls_sec/stock/__init__.py
ls_sec/stock/_etc.py
ls_sec/stock/_market.py
ls_sec-0.1.0.dist-info/METADATA
ls_sec-0.1.0.dist-info/WHEEL
ls_sec-0.1.0.dist-info/top_level.txt
ls_sec-0.1.0.dist-info/RECORD
