Metadata-Version: 2.1
Name: ls_sec
Version: 0.1.0
Summary: ls security open api
Author-email: Jungwoo Yang <jwyang0213@gmail.com>
Requires-Dist: pandas
Requires-Dist: aiofiles
Provides-Extra: dev
Requires-Dist: pytest>=6.2.2; extra == "dev"
Requires-Dist: black; extra == "dev"
Requires-Dist: flake8; extra == "dev"
Requires-Dist: isort; extra == "dev"
